django_openstack_auth-3.6.1.dist-info/METADATA
django_openstack_auth-3.6.1.dist-info/RECORD
django_openstack_auth-3.6.1.dist-info/WHEEL
django_openstack_auth-3.6.1.dist-info/pbr.json
django_openstack_auth-3.6.1.dist-info/top_level.txt
openstack_auth/__init__.py
openstack_auth/backend.py
openstack_auth/exceptions.py
openstack_auth/forms.py
openstack_auth/models.py
openstack_auth/policy.py
openstack_auth/urls.py
openstack_auth/user.py
openstack_auth/utils.py
openstack_auth/views.py
openstack_auth/locale/cs/LC_MESSAGES/django.po
openstack_auth/locale/de/LC_MESSAGES/django.po
openstack_auth/locale/en_AU/LC_MESSAGES/django.po
openstack_auth/locale/en_GB/LC_MESSAGES/django.po
openstack_auth/locale/es/LC_MESSAGES/django.po
openstack_auth/locale/es_MX/LC_MESSAGES/django.po
openstack_auth/locale/fr/LC_MESSAGES/django.po
openstack_auth/locale/id/LC_MESSAGES/django.po
openstack_auth/locale/it/LC_MESSAGES/django.po
openstack_auth/locale/ja/LC_MESSAGES/django.po
openstack_auth/locale/ko_KR/LC_MESSAGES/django.po
openstack_auth/locale/nl_NL/LC_MESSAGES/django.po
openstack_auth/locale/pa_IN/LC_MESSAGES/django.po
openstack_auth/locale/pl_PL/LC_MESSAGES/django.po
openstack_auth/locale/pt_BR/LC_MESSAGES/django.po
openstack_auth/locale/ru/LC_MESSAGES/django.po
openstack_auth/locale/tr_TR/LC_MESSAGES/django.po
openstack_auth/locale/uk/LC_MESSAGES/django.po
openstack_auth/locale/zh_CN/LC_MESSAGES/django.po
openstack_auth/locale/zh_TW/LC_MESSAGES/django.po
openstack_auth/plugin/__init__.py
openstack_auth/plugin/base.py
openstack_auth/plugin/k2k.py
openstack_auth/plugin/password.py
openstack_auth/plugin/token.py
openstack_auth/tests/__init__.py
openstack_auth/tests/data_v2.py
openstack_auth/tests/data_v3.py
openstack_auth/tests/models.py
openstack_auth/tests/run_tests.py
openstack_auth/tests/settings.py
openstack_auth/tests/tests.py
openstack_auth/tests/urls.py
openstack_auth/tests/conf/keystone_policy.json
openstack_auth/tests/conf/no_default_policy.json
openstack_auth/tests/conf/nova_policy.json
openstack_auth/tests/conf/policy.v3cloudsample.json
openstack_auth/tests/conf/with_default_policy.json
openstack_auth/tests/templates/auth/blank.html
