Metadata-Version: 2.1
Name: django-openstack-auth
Version: 3.6.1
Summary: Django authentication backend for use with OpenStack Identity
Home-page: http://www.openstack.org/
Author: OpenStack
Author-email: openstack-dev@lists.openstack.org
License: UNKNOWN
Platform: UNKNOWN
Classifier: Development Status :: 5 - Production/Stable
Classifier: Environment :: OpenStack
Classifier: Framework :: Django
Classifier: Intended Audience :: Developers
Classifier: Intended Audience :: Information Technology
Classifier: Intended Audience :: System Administrators
Classifier: License :: OSI Approved :: Apache Software License
Classifier: Operating System :: OS Independent
Classifier: Operating System :: POSIX :: Linux
Classifier: Programming Language :: Python
Classifier: Programming Language :: Python :: 2
Classifier: Programming Language :: Python :: 2.7
Classifier: Programming Language :: Python :: 3
Classifier: Programming Language :: Python :: 3.4
Classifier: Programming Language :: Python :: 3.5
Classifier: Topic :: Internet :: WWW/HTTP
Requires-Dist: pbr (!=2.1.0,>=2.0.0)
Requires-Dist: Django (<2.0,>=1.8)
Requires-Dist: oslo.config (!=4.3.0,!=4.4.0,>=4.0.0)
Requires-Dist: oslo.policy (>=1.23.0)
Requires-Dist: python-keystoneclient (>=3.8.0)
Requires-Dist: keystoneauth1 (>=3.1.0)
Requires-Dist: six (>=1.9.0)
